order_receipt_cu/__init__.py
order_receipt_cu/__main__.py
order_receipt_cu-0.1.0.dist-info/METADATA
order_receipt_cu-0.1.0.dist-info/WHEEL
order_receipt_cu-0.1.0.dist-info/entry_points.txt
order_receipt_cu-0.1.0.dist-info/top_level.txt
order_receipt_cu-0.1.0.dist-info/RECORD
